eykthyr/__about__.py
eykthyr/__init__.py
eykthyr/data_strage.py
eykthyr/development.py
eykthyr/embedding.py
eykthyr/eykthyr.py
eykthyr/model.py
eykthyr/modified_VelocytoLoom_class.py
eykthyr/plotting.py
eykthyr/plotting_utils.py
eykthyr/pseudotime.py
eykthyr/scatter_to_grid.py
eykthyr/util.py
eykthyr-0.0.4.dist-info/METADATA
eykthyr-0.0.4.dist-info/WHEEL
eykthyr-0.0.4.dist-info/entry_points.txt
eykthyr-0.0.4.dist-info/licenses/LICENSE
eykthyr-0.0.4.dist-info/RECORD
