Metadata-Version: 2.3
Name: eykthyr
Version: 0.0.4
Summary: Eykthyr: Revealing transcriptional regulators of spatial gene programs
Project-URL: Homepage, https://github.com/gkrieg/eykthyr
Project-URL: Bug Tracker, https://github.com/gkrieg/eykthyr/issues
Author-email: Spencer Krieger <spencer.krieger@gmail.com>
License: MIT License
Classifier: License :: OSI Approved :: MIT License
Classifier: Operating System :: OS Independent
Classifier: Programming Language :: Python :: 3
Requires-Python: >=3.8
Requires-Dist: anndata>=0.9.1
Requires-Dist: cython>=3.0.11
Requires-Dist: louvain>=0.8.0
Requires-Dist: matplotlib>=3.7.0
Requires-Dist: numpy>=1.20.1
Requires-Dist: pandas>=1.5.2
Requires-Dist: popari>=0.0.72
Requires-Dist: scanpy>=1.9.2
Requires-Dist: scikit-learn>=0.24.1
Requires-Dist: scipy>=1.7.1
Requires-Dist: seaborn>=0.11.1
Requires-Dist: squidpy>=1.2.3
Requires-Dist: torch>=1.13.0
Requires-Dist: tqdm>=4.60.0
Requires-Dist: umap-learn>=0.5.1
Provides-Extra: simulation
Requires-Dist: ipycanvas; extra == 'simulation'
Requires-Dist: jupyterlab; extra == 'simulation'
Provides-Extra: with-velocyto
Requires-Dist: velocyto>=0.17.17; extra == 'with-velocyto'
